{
    "description": "Dubrovnik Annals ISSN:1331-3878 Historical Contributions ISSN:0351-9767 Histria antiqua ISSN:1331-4270 Histria archaeologica ISSN:0350-6320 HISTRIA The Istrian Historical Society Review ISSN:1848-1183 Holon e-ISSN:1848-3518 Interdisciplinary Description of Complex Systems ISSN:1334-4676 e-ISSN:1334-4676 Journal - Institute of Croatian History ISSN:0353-295X Journal of Dalmatian archaeology and history ISSN:1845-7789 Journal of the Zagreb Archaeological Museum ISSN:0350-7165 Media, Culture and Public Relations ISSN:1333-6371 Opuscula Archaeologica Papers of the Department of Archaeology ISSN:0473-0992 Podravina: scientific multidisciplinary research journal ISSN:1333-5286 Portal, the Yearbook of the Croatian Conservation Institute Povijesni zbornik: godi\u0161njak za kulturu i povijesno naslje\u0111e ISSN:1846-3819 Radovi / Institute for Historical Sciences of the Croatian Academy of Sciences and Arts in Zadar ISSN:1330-0474 Starohrvatska prosvjeta ISSN:0351-4536 The Museum Courier. Organ of the Museums of Northwestern Croatia ISSN:0350-9370 The Preservation of Cultural Heritage in Croatia ISSN:0350-2589 The Review of Senj ISSN:0582-673X The Yearbook of the Vara\u017edin City Museum ISSN:0351-7926", 
    "domain": "hrcak.srce.hr", 
    "history": [
        "2015-06-03T22:29:11.099894: Data automatically parsed from content of http://ancientworldonline.blogspot.com/2009/01/croatian-open-access-archaeology.html. (walk_to_json.py)"
    ], 
    "identifiers": {
        "issn": {
            "electronic": [
                "1846-3819", 
                "1334-4676", 
                "1848-3518"
            ], 
            "generic": [
                "0353-295X", 
                "0350-6320", 
                "1331-3878", 
                "0351-9767", 
                "0351-4536", 
                "1330-0474", 
                "0350-2589", 
                "1845-7789", 
                "1333-5286", 
                "1331-4270", 
                "0473-0992", 
                "0350-7165", 
                "1848-1183", 
                "0350-9370", 
                "0351-7926", 
                "0582-673X", 
                "1333-6371"
            ]
        }
    }, 
    "keywords": [
        "Balkans", 
        "Croatia", 
        "Croatian", 
        "Zagreb", 
        "archaeology", 
        "conservation", 
        "cultural heritage", 
        "culture", 
        "heritage", 
        "history", 
        "journal", 
        "museums", 
        "open access", 
        "preservation"
    ], 
    "language": [
        "en", 
        1.0
    ], 
    "provenance": [
        {
            "fields": [
                "description", 
                "domain", 
                "history", 
                "identifiers", 
                "keywords", 
                "language", 
                "provenance", 
                "related_resources", 
                "subordinate_resources", 
                "title", 
                "url", 
                "zotero_id"
            ], 
            "resource": "tag:blogger.com,1999:blog-116259103207720939.post-4951233991735144268", 
            "resource_date": "2012-11-30T10:12:29.204-05:00", 
            "term": "http://purl.org/spar/cito/citesAsDataSource", 
            "when": "2015-06-03T22:29:11.100506"
        }, 
        {
            "resource": "http://ancientworldonline.blogspot.com/2009/01/croatian-open-access-archaeology.html", 
            "resource_date": "2012-11-30T10:12:29.204-05:00", 
            "term": "http://purl.org/spar/cito/citesAsMetadataDocument", 
            "when": "2015-06-03T22:29:11.100514"
        }
    ], 
    "related_resources": [], 
    "subordinate_resources": [], 
    "title": "Dubrovnik Annals", 
    "url": "http://hrcak.srce.hr/dubrovnik-annals", 
    "zotero_id": null
}